just_for_fun/__init__.py
just_for_fun/module.py
just_for_fun/ABSA/__init__.py
just_for_fun/ABSA/api.py
just_for_fun-0.0.0.dist-info/LICENSE
just_for_fun-0.0.0.dist-info/METADATA
just_for_fun-0.0.0.dist-info/WHEEL
just_for_fun-0.0.0.dist-info/top_level.txt
just_for_fun-0.0.0.dist-info/RECORD
