Metadata-Version: 2.1
Name: just-for-fun
Version: 0.0.0
Summary: My short description for my project.
Home-page: https://github.com/vito19960522/just_for_fun
Author: Vito
Author-email: 1240505429@qq.com
License: MIT
Platform: UNKNOWN
Classifier: License :: OSI Approved :: MIT License
Classifier: Programming Language :: Python
Classifier: Programming Language :: Python :: 3
Classifier: Programming Language :: Python :: 3.6
Classifier: Programming Language :: Python :: Implementation :: CPython
Classifier: Programming Language :: Python :: Implementation :: PyPy
Requires-Python: >=3.6.0
